min/__init__.py
min/cli/__init__.py
min/cli/cli.py
min/cli/config.py
min/cli/io_ops.py
min/docs/commands/apropos.txt
min/docs/commands/cat.txt
min/docs/commands/cd.txt
min/docs/commands/chgrp.txt
min/docs/commands/chmod.txt
min/docs/commands/chown.txt
min/docs/commands/cp.txt
min/docs/commands/curl.txt
min/docs/commands/cut.txt
min/docs/commands/date.txt
min/docs/commands/diff.txt
min/docs/commands/du.txt
min/docs/commands/echo.txt
min/docs/commands/export.txt
min/docs/commands/factor.txt
min/docs/commands/file.txt
min/docs/commands/find.txt
min/docs/commands/git-add.txt
min/docs/commands/git-blame.txt
min/docs/commands/git-branch.txt
min/docs/commands/git-checkout.txt
min/docs/commands/git-clean.txt
min/docs/commands/git-clone.txt
min/docs/commands/git-commit.txt
min/docs/commands/git-config.txt
min/docs/commands/git-diff.txt
min/docs/commands/git-grep.txt
min/docs/commands/git-log.txt
min/docs/commands/git-push.txt
min/docs/commands/git-reflog.txt
min/docs/commands/git-remote.txt
min/docs/commands/git-reset.txt
min/docs/commands/git-rev-parse.txt
min/docs/commands/git-show.txt
min/docs/commands/git-stash.txt
min/docs/commands/git-status.txt
min/docs/commands/grep.txt
min/docs/commands/head.txt
min/docs/commands/history.txt
min/docs/commands/host.txt
min/docs/commands/iconv.txt
min/docs/commands/id.txt
min/docs/commands/less.txt
min/docs/commands/ln.txt
min/docs/commands/locate.txt
min/docs/commands/ls.txt
min/docs/commands/lsb_release.txt
min/docs/commands/lshw.txt
min/docs/commands/lsof.txt
min/docs/commands/lspci.txt
min/docs/commands/lsusb.txt
min/docs/commands/man.txt
min/docs/commands/mkdir.txt
min/docs/commands/mv.txt
min/docs/commands/ncal.txt
min/docs/commands/nl.txt
min/docs/commands/passwd.txt
min/docs/commands/popd.txt
min/docs/commands/printenv.txt
min/docs/commands/ps.txt
min/docs/commands/pushd.txt
min/docs/commands/pwd.txt
min/docs/commands/rename.txt
min/docs/commands/rm.txt
miniman-0.0.8.dist-info/METADATA
miniman-0.0.8.dist-info/RECORD
miniman-0.0.8.dist-info/WHEEL
miniman-0.0.8.dist-info/entry_points.txt
miniman-0.0.8.dist-info/top_level.txt
