Metadata-Version: 2.1
Name: miniman
Version: 0.0.8
Summary: minimal manpages.
Home-page: UNKNOWN
Author: Michael Leue
Author-email: michael@mleue.com
License: UNKNOWN
Keywords: manpage minimal man
Platform: UNKNOWN
Classifier: Intended Audience :: Developers
Classifier: Topic :: Software Development :: Documentation
Classifier: Programming Language :: Python :: 3
Classifier: License :: OSI Approved :: MIT License
Classifier: Operating System :: OS Independent
